graphql_query/__info__.py
graphql_query/__init__.py
graphql_query/__version__.py
graphql_query/base_model.py
graphql_query/py.typed
graphql_query/templates.py
graphql_query/types.py
graphql_query/templates/argument_key_argument.jinja2
graphql_query/templates/argument_key_arguments.jinja2
graphql_query/templates/argument_key_objects.jinja2
graphql_query/templates/argument_key_value.jinja2
graphql_query/templates/argument_key_values.jinja2
graphql_query/templates/argument_key_variable.jinja2
graphql_query/templates/directive.jinja2
graphql_query/templates/field.jinja2
graphql_query/templates/fragment.jinja2
graphql_query/templates/inline_fragment.jinja2
graphql_query/templates/operation.jinja2
graphql_query/templates/query.jinja2
graphql_query/templates/variable.jinja2
graphql_query-1.3.2.dist-info/METADATA
graphql_query-1.3.2.dist-info/WHEEL
graphql_query-1.3.2.dist-info/licenses/LICENSE
graphql_query-1.3.2.dist-info/RECORD
