Metadata-Version: 2.3
Name: graphql_query
Version: 1.3.2
Summary: Complete Domain Specific Language (DSL) for GraphQL query in Python.
Project-URL: Homepage, https://github.com/denisart/graphql-query
Project-URL: Documentation, https://denisart.github.io/graphql-query/
Project-URL: Source, https://github.com/denisart/graphql-query
Author-email: "Denis A. Artyushin" <artyushinden@gmail.com>
License-Expression: MIT
License-File: LICENSE
Keywords: code-generation,codegen,dsl,graphql,graphql-query,graphql-query-builder,pydantic,python,query-builder,query-generation,query-generator
Classifier: Development Status :: 5 - Production/Stable
Classifier: Environment :: MacOS X
Classifier: Framework :: Pydantic
Classifier: Framework :: Pydantic :: 2
Classifier: License :: OSI Approved :: MIT License
Classifier: Operating System :: OS Independent
Classifier: Programming Language :: Python
Classifier: Programming Language :: Python :: 3
Classifier: Programming Language :: Python :: 3 :: Only
Classifier: Programming Language :: Python :: 3.8
Classifier: Programming Language :: Python :: 3.9
Classifier: Programming Language :: Python :: 3.10
Classifier: Programming Language :: Python :: 3.11
Classifier: Programming Language :: Python :: 3.12
Classifier: Topic :: Software Development :: Libraries
Classifier: Topic :: Software Development :: Libraries :: Python Modules
Requires-Python: >=3.8
Requires-Dist: jinja2<3.2,>=3.1
Requires-Dist: pydantic>=2
Provides-Extra: dev
Requires-Dist: black; extra == 'dev'
Requires-Dist: mypy; extra == 'dev'
Requires-Dist: pylint-pydantic; extra == 'dev'
Requires-Dist: ruff; extra == 'dev'
Requires-Dist: wheel; extra == 'dev'
Provides-Extra: docs
Requires-Dist: mkdocs; extra == 'docs'
Requires-Dist: mkdocs-material; extra == 'docs'
Provides-Extra: test
Requires-Dist: pytest; extra == 'test'
Requires-Dist: pytest-cov; extra == 'test'
Requires-Dist: pytest-mock; extra == 'test'
